pyscenewriter-0.0.8.dist-info/METADATA
pyscenewriter-0.0.8.dist-info/WHEEL
pyscenewriter/__init__.py
pyscenewriter/pyscenewriter.pypy38-pp73-arm-linux-gnu.so
pyscenewriter-0.0.8.dist-info/RECORD
